odoo/addons/commission_formula/README.rst
odoo/addons/commission_formula/__init__.py
odoo/addons/commission_formula/__manifest__.py
odoo/addons/commission_formula/demo/commission_demo.xml
odoo/addons/commission_formula/i18n/ca.po
odoo/addons/commission_formula/i18n/commission_formula.pot
odoo/addons/commission_formula/i18n/de.po
odoo/addons/commission_formula/i18n/el_GR.po
odoo/addons/commission_formula/i18n/es.po
odoo/addons/commission_formula/i18n/es_AR.po
odoo/addons/commission_formula/i18n/fi.po
odoo/addons/commission_formula/i18n/fr.po
odoo/addons/commission_formula/i18n/it.po
odoo/addons/commission_formula/i18n/pt.po
odoo/addons/commission_formula/i18n/pt_BR.po
odoo/addons/commission_formula/i18n/pt_PT.po
odoo/addons/commission_formula/i18n/ru.po
odoo/addons/commission_formula/i18n/sale_commission_formula.pot
odoo/addons/commission_formula/i18n/sl.po
odoo/addons/commission_formula/i18n/tr.po
odoo/addons/commission_formula/i18n/tr_TR.po
odoo/addons/commission_formula/i18n/zh_CN.po
odoo/addons/commission_formula/models/__init__.py
odoo/addons/commission_formula/models/commission.py
odoo/addons/commission_formula/models/commission_mixin.py
odoo/addons/commission_formula/readme/CONTRIBUTORS.md
odoo/addons/commission_formula/readme/DESCRIPTION.md
odoo/addons/commission_formula/readme/USAGE.md
odoo/addons/commission_formula/static/description/icon.png
odoo/addons/commission_formula/static/description/icon.svg
odoo/addons/commission_formula/static/description/index.html
odoo/addons/commission_formula/static/src/css/commission_formula.css
odoo/addons/commission_formula/views/commission_view.xml
odoo_addon_commission_formula-17.0.1.0.0.8.dist-info/METADATA
odoo_addon_commission_formula-17.0.1.0.0.8.dist-info/WHEEL
odoo_addon_commission_formula-17.0.1.0.0.8.dist-info/top_level.txt
odoo_addon_commission_formula-17.0.1.0.0.8.dist-info/RECORD
